Metadata-Version: 2.1
Name: litecollections
Version: 2022.5.15.5
Summary: python collections except its all backed by sqlite
Home-page: https://github.com/CodyKochmann/litecollections
Author: Cody Kochmann
Author-email: kochmanncody@gmail.com
Maintainer: Cody Kochmann
Maintainer-email: kochmanncody@gmail.com
License: MIT License
Download-URL: https://github.com/CodyKochmann/litecollections/tarball/2022.5.15.5
Keywords: sqlite,collections,persistent,performance,scale,datascience,acid,database
Platform: UNKNOWN
License-File: LICENSE
